camora/__init__.py
camora/app.py
camora/errors.py
camora/interfaces.py
camora/models.py
camora/utils.py
camora/redis/__init__.py
camora/redis/broker.py
camora-0.1.0.dist-info/LICENSE
camora-0.1.0.dist-info/METADATA
camora-0.1.0.dist-info/WHEEL
camora-0.1.0.dist-info/top_level.txt
camora-0.1.0.dist-info/RECORD
