Metadata-Version: 2.1
Name: camora
Version: 0.1.0
Summary: Lightweight task scheduler
Author: Piotr Tobiasz
Author-email: piotr.tobiasz.dev@gmail.com
License: MIT
Classifier: Programming Language :: Python :: 3
Classifier: License :: OSI Approved :: MIT License
Classifier: Operating System :: OS Independent
Requires-Python: >=3.7.0
License-File: LICENSE
Requires-Dist: pydantic ==2.5.2
Provides-Extra: redis
Requires-Dist: redis ==5.0.1 ; extra == 'redis'
